
// class version 49.0 (49)
// access flags 0x20
class biz/markov/thinking/strings/Ex01_SprinklerSystem2 {

  // compiled from: Ex01.java

  // access flags 0x2
  private Ljava/lang/String; valve1

  // access flags 0x2
  private Ljava/lang/String; valve2

  // access flags 0x2
  private Ljava/lang/String; valve3

  // access flags 0x2
  private Ljava/lang/String; valve4

  // access flags 0x2
  private Lbiz/markov/thinking/strings/WaterSource; source

  // access flags 0x2
  private I i

  // access flags 0x2
  private F f

  // access flags 0x0
  <init>()V
   L0
    LINENUMBER 28 L0
    ALOAD 0
    INVOKESPECIAL java/lang/Object.<init> ()V
   L1
    LINENUMBER 30 L1
    ALOAD 0
    NEW biz/markov/thinking/strings/WaterSource
    DUP
    INVOKESPECIAL biz/markov/thinking/strings/WaterSource.<init> ()V
    PUTFIELD biz/markov/thinking/strings/Ex01_SprinklerSystem2.source : Lbiz/markov/thinking/strings/WaterSource;
    RETURN
   L2
    LOCALVARIABLE this Lbiz/markov/thinking/strings/Ex01_SprinklerSystem2; L0 L2 0
    MAXSTACK = 3
    MAXLOCALS = 1

  // access flags 0x1
  public toString()Ljava/lang/String;
   L0
    LINENUMBER 34 L0
    NEW java/lang/StringBuilder
    DUP
    LDC "valve1 = "
    INVOKESPECIAL java/lang/StringBuilder.<init> (Ljava/lang/String;)V
    ASTORE 1
   L1
    LINENUMBER 35 L1
    ALOAD 1
    ALOAD 0
    GETFIELD biz/markov/thinking/strings/Ex01_SprinklerSystem2.valve1 : Ljava/lang/String;
    INVOKEVIRTUAL java/lang/StringBuilder.append (Ljava/lang/String;)Ljava/lang/StringBuilder;
    POP
   L2
    LINENUMBER 36 L2
    ALOAD 1
    LDC " "
    INVOKEVIRTUAL java/lang/StringBuilder.append (Ljava/lang/String;)Ljava/lang/StringBuilder;
    POP
   L3
    LINENUMBER 37 L3
    ALOAD 1
    LDC "valve2 = "
    INVOKEVIRTUAL java/lang/StringBuilder.append (Ljava/lang/String;)Ljava/lang/StringBuilder;
    POP
   L4
    LINENUMBER 38 L4
    ALOAD 1
    ALOAD 0
    GETFIELD biz/markov/thinking/strings/Ex01_SprinklerSystem2.valve2 : Ljava/lang/String;
    INVOKEVIRTUAL java/lang/StringBuilder.append (Ljava/lang/String;)Ljava/lang/StringBuilder;
    POP
   L5
    LINENUMBER 39 L5
    ALOAD 1
    LDC " "
    INVOKEVIRTUAL java/lang/StringBuilder.append (Ljava/lang/String;)Ljava/lang/StringBuilder;
    POP
   L6
    LINENUMBER 40 L6
    ALOAD 1
    LDC "valve3 = "
    INVOKEVIRTUAL java/lang/StringBuilder.append (Ljava/lang/String;)Ljava/lang/StringBuilder;
    POP
   L7
    LINENUMBER 41 L7
    ALOAD 1
    ALOAD 0
    GETFIELD biz/markov/thinking/strings/Ex01_SprinklerSystem2.valve3 : Ljava/lang/String;
    INVOKEVIRTUAL java/lang/StringBuilder.append (Ljava/lang/String;)Ljava/lang/StringBuilder;
    POP
   L8
    LINENUMBER 42 L8
    ALOAD 1
    LDC " "
    INVOKEVIRTUAL java/lang/StringBuilder.append (Ljava/lang/String;)Ljava/lang/StringBuilder;
    POP
   L9
    LINENUMBER 43 L9
    ALOAD 1
    LDC "valve4 = "
    INVOKEVIRTUAL java/lang/StringBuilder.append (Ljava/lang/String;)Ljava/lang/StringBuilder;
    POP
   L10
    LINENUMBER 44 L10
    ALOAD 1
    ALOAD 0
    GETFIELD biz/markov/thinking/strings/Ex01_SprinklerSystem2.valve4 : Ljava/lang/String;
    INVOKEVIRTUAL java/lang/StringBuilder.append (Ljava/lang/String;)Ljava/lang/StringBuilder;
    POP
   L11
    LINENUMBER 45 L11
    ALOAD 1
    LDC "\n"
    INVOKEVIRTUAL java/lang/StringBuilder.append (Ljava/lang/String;)Ljava/lang/StringBuilder;
    POP
   L12
    LINENUMBER 46 L12
    ALOAD 1
    LDC "i = "
    INVOKEVIRTUAL java/lang/StringBuilder.append (Ljava/lang/String;)Ljava/lang/StringBuilder;
    POP
   L13
    LINENUMBER 47 L13
    ALOAD 1
    ALOAD 0
    GETFIELD biz/markov/thinking/strings/Ex01_SprinklerSystem2.i : I
    INVOKEVIRTUAL java/lang/StringBuilder.append (I)Ljava/lang/StringBuilder;
    POP
   L14
    LINENUMBER 48 L14
    ALOAD 1
    LDC " "
    INVOKEVIRTUAL java/lang/StringBuilder.append (Ljava/lang/String;)Ljava/lang/StringBuilder;
    POP
   L15
    LINENUMBER 49 L15
    ALOAD 1
    LDC "f = "
    INVOKEVIRTUAL java/lang/StringBuilder.append (Ljava/lang/String;)Ljava/lang/StringBuilder;
    POP
   L16
    LINENUMBER 50 L16
    ALOAD 1
    ALOAD 0
    GETFIELD biz/markov/thinking/strings/Ex01_SprinklerSystem2.f : F
    INVOKEVIRTUAL java/lang/StringBuilder.append (F)Ljava/lang/StringBuilder;
    POP
   L17
    LINENUMBER 51 L17
    ALOAD 1
    LDC " "
    INVOKEVIRTUAL java/lang/StringBuilder.append (Ljava/lang/String;)Ljava/lang/StringBuilder;
    POP
   L18
    LINENUMBER 52 L18
    ALOAD 1
    LDC "source = "
    INVOKEVIRTUAL java/lang/StringBuilder.append (Ljava/lang/String;)Ljava/lang/StringBuilder;
    POP
   L19
    LINENUMBER 53 L19
    ALOAD 1
    ALOAD 0
    GETFIELD biz/markov/thinking/strings/Ex01_SprinklerSystem2.source : Lbiz/markov/thinking/strings/WaterSource;
    INVOKEVIRTUAL java/lang/StringBuilder.append (Ljava/lang/Object;)Ljava/lang/StringBuilder;
    POP
   L20
    LINENUMBER 55 L20
    ALOAD 1
    INVOKEVIRTUAL java/lang/StringBuilder.toString ()Ljava/lang/String;
    ARETURN
   L21
    LOCALVARIABLE this Lbiz/markov/thinking/strings/Ex01_SprinklerSystem2; L0 L21 0
    LOCALVARIABLE sb Ljava/lang/StringBuilder; L1 L21 1
    MAXSTACK = 3
    MAXLOCALS = 2
}
